otpcr/brokers.py
otpcr/caching.py
otpcr/clients.py
otpcr/command.py
otpcr/handler.py
otpcr/methods.py
otpcr/objects.py
otpcr/package.py
otpcr/serials.py
otpcr/threads.py
otpcr/utility.py
otpcr/workdir.py
otpcr/modules/flt.py
otpcr/modules/fnd.py
otpcr/modules/irc.py
otpcr/modules/log.py
otpcr/modules/lst.py
otpcr/modules/mdl.py
otpcr/modules/mod.py
otpcr/modules/pth.py
otpcr/modules/req.py
otpcr/modules/rss.py
otpcr/modules/sil.py
otpcr/modules/slg.py
otpcr/modules/tdo.py
otpcr/modules/thr.py
otpcr/modules/upt.py
otpcr/modules/web.py
otpcr/network/main.py
otpcr/network/html/about.html
otpcr/network/html/evidence.html
otpcr/network/html/genindex-all.html
otpcr/network/html/genindex.html
otpcr/network/html/guilty.html
otpcr/network/html/index.html
otpcr/network/html/manual.html
otpcr/network/html/objects.inv
otpcr/network/html/pubchem.html
otpcr/network/html/reconsider.html
otpcr/network/html/request.html
otpcr/network/html/robots.txt
otpcr/network/html/search.html
otpcr/network/html/searchindex.js
otpcr/network/html/writings.html
otpcr/network/html/_images/ECHAabilify.png
otpcr/network/html/_images/ECHAclozapine.png
otpcr/network/html/_images/ECHAhaldol.png
otpcr/network/html/_images/ECHAzyprexa.png
otpcr/network/html/_images/OTP111.png
otpcr/network/html/_images/OTP222.png
otpcr/network/html/_images/abilifypubchem.png
otpcr/network/html/_images/ack3.png
otpcr/network/html/_images/bevestigd.jpg
otpcr/network/html/_images/clozapinepubchem.png
otpcr/network/html/_images/genocide.png
otpcr/network/html/_images/haldolpubchem.png
otpcr/network/html/_images/informed.jpg
otpcr/network/html/_images/kamer2.png
otpcr/network/html/_images/skull3.png
otpcr/network/html/_images/zyprexapubchem.png
otpcr/network/html/_static/alabaster.css
otpcr/network/html/_static/basic.css
otpcr/network/html/_static/custom.css
otpcr/network/html/_static/doctools.js
otpcr/network/html/_static/documentation_options.js
otpcr/network/html/_static/file.png
otpcr/network/html/_static/genocide.css
otpcr-94.dist-info/METADATA
otpcr-94.dist-info/WHEEL
otpcr-94.dist-info/entry_points.txt
otpcr-94.dist-info/top_level.txt
otpcr-94.dist-info/RECORD
