Metadata-Version: 2.4
Name: otpcr
Version: 94
Summary: Since 4 March 2019
Author-email: Bart Thate <bthate@dds.nl>
License-Expression: Unlicense
Project-URL: home, https://pypi.org/project/otpcr
Project-URL: bugs, https://github.com/otpcr/otpcr/issues
Project-URL: source, https://github.com/otpcr/otpcr
Classifier: Development Status :: 3 - Alpha
Classifier: Operating System :: Unix
Classifier: Programming Language :: Python
Classifier: Topic :: Utilities
